Dataflow verilog/combination.v
module combination (
    input  A, B, C, D,
    output F
);

assign F = (~B & ~D) |
           (A & ~B & ~C) |
           (A & B & C & D);

endmodule

Dataflow verilog/combination_tb.v
`timescale 1ns/1ps

module tb_boolean_func;

reg A, B, C, D;
wire F_data, F_beh;

// Instantiate DUTs
combination DUT (
    .A(A), .B(B), .C(C), .D(D),
    .F(F_data)
);



integer i;

initial begin
    // 1️ Create waveform dump file
    $dumpfile("boolean_func.vcd");

    // 2️ Dump all variables in this module and below
    $dumpvars(0, tb_boolean_func);

    // Optional: dump specific signals only
    // $dumpvars(1, A, B, C, D, F_data, F_beh);

    $display("A B C D | Dataflow");
    $display("-------------------------------");

    for (i = 0; i < 16; i = i + 1) begin
        {A, B, C, D} = i;
        #10;
        $display("%b %b %b %b |    %b         %b",
                 A, B, C, D, F_data, F_beh);
    end

    $finish;
end

endmodule

Dataflow verilog/boolean_func.vcd
$date
	Thu Jan 29 18:28:46 2026
$end
$version
	Icarus Verilog
$end
$timescale
	1ps
$end
$scope module tb_boolean_func $end
$var wire 1 ! F_beh $end
$var wire 1 " F_data $end
$var reg 1 # A $end
$var reg 1 $ B $end
$var reg 1 % C $end
$var reg 1 & D $end
$var integer 32 ' i [31:0] $end
$scope module DUT $end
$var wire 1 # A $end
$var wire 1 $ B $end
$var wire 1 % C $end
$var wire 1 & D $end
$var wire 1 " F $end
$upscope $end
$upscope $end
$enddefinitions $end
#0
$dumpvars
b0 '
0&
0%
0$
0#
1"
z!
$end
#10000
0"
1&
b1 '
#20000
1"
1%
0&
b10 '
#30000
0"
1&
b11 '
#40000
1$
0%
0&
b100 '
#50000
1&
b101 '
#60000
1%
0&
b110 '
#70000
1&
b111 '
#80000
1"
1#
0$
0%
0&
b1000 '
#90000
1&
b1001 '
#100000
1%
0&
b1010 '
#110000
0"
1&
b1011 '
#120000
0"
1$
0%
0&
b1100 '
#130000
1&
b1101 '
#140000
1%
0&
b1110 '
#150000
1"
1&
b1111 '
#160000
b10000 '
